astarteplatform/msghub/astarte_data_pb2.py
astarteplatform/msghub/astarte_data_pb2.pyi
astarteplatform/msghub/astarte_data_pb2_grpc.py
astarteplatform/msghub/astarte_message_pb2.py
astarteplatform/msghub/astarte_message_pb2.pyi
astarteplatform/msghub/astarte_message_pb2_grpc.py
astarteplatform/msghub/config_pb2.py
astarteplatform/msghub/config_pb2.pyi
astarteplatform/msghub/config_pb2_grpc.py
astarteplatform/msghub/interface_pb2.py
astarteplatform/msghub/interface_pb2.pyi
astarteplatform/msghub/interface_pb2_grpc.py
astarteplatform/msghub/message_hub_error_pb2.py
astarteplatform/msghub/message_hub_error_pb2.pyi
astarteplatform/msghub/message_hub_error_pb2_grpc.py
astarteplatform/msghub/message_hub_service_pb2.py
astarteplatform/msghub/message_hub_service_pb2.pyi
astarteplatform/msghub/message_hub_service_pb2_grpc.py
astarteplatform/msghub/node_pb2.py
astarteplatform/msghub/node_pb2.pyi
astarteplatform/msghub/node_pb2_grpc.py
astarteplatform/msghub/property_pb2.py
astarteplatform/msghub/property_pb2.pyi
astarteplatform/msghub/property_pb2_grpc.py
astarte_message_hub_proto-0.10.1.dist-info/METADATA
astarte_message_hub_proto-0.10.1.dist-info/WHEEL
astarte_message_hub_proto-0.10.1.dist-info/top_level.txt
astarte_message_hub_proto-0.10.1.dist-info/RECORD
