Metadata-Version: 2.4
Name: astarte_message_hub_proto
Version: 0.10.1
Summary: Astarte message hub protocol buffers for Python
Author-email: Simone Orru <simone.orru@secomind.com>
Project-URL: Source, https://github.com/astarte-platform/astarte-message-hub-proto
Classifier: License :: OSI Approved :: Apache Software License
Requires-Python: >=3.8
Requires-Dist: grpcio==1.69.0
Requires-Dist: protobuf==5.29.5
Provides-Extra: generation
Requires-Dist: grpcio-tools==1.69.0; extra == "generation"
Requires-Dist: termcolor==3.1.0; extra == "generation"
Provides-Extra: static
Requires-Dist: black; extra == "static"
Requires-Dist: pylint; extra == "static"
Requires-Dist: termcolor; extra == "static"
